[{"firstName": "Lawrence", "lastName": "Semakula", "middleName": null, "email": "", "job": "Accountant General", "roomContact": "7115", "office": "Accountant General's Office"}, {"firstName": "Godfrey", "lastName": "Ssemugoma", "middleName": null, "email": "", "job": "Ag.Director/FMS", "roomContact": "7117", "office": "Financial Management Services"}, {"firstName": "Aiden", "lastName": "Rujumba", "middleName": null, "email": "", "job": "Ag. C/FMSD", "roomContact": "7259", "office": "Financial Management Services"}, {"firstName": "Jane", "lastName": "Enyaku", "middleName": null, "email": "", "job": "Personal Secretary/AG", "roomContact": "7919", "office": "Accountant General's Office"}, {"firstName": "Arthur", "lastName": "Mugweri", "middleName": null, "email": "", "job": "Ag. Comm/IFMS", "roomContact": "7933", "office": "Management Information Systems-MIS/IFMS"}, {"firstName": "Daniel", "lastName": "Lubowa", "middleName": null, "email": "", "job": "Sen. Sytems Analyst", "roomContact": "7917", "office": "Management Information Systems-MIS/IFMS"}, {"firstName": "Edward", "lastName": "Oweyesigire", "middleName": null, "email": "", "job": "Office Attendant", "roomContact": "7256", "office": "Accountant General's Office"}, {"firstName": "Robert", "lastName": "Izimba", "middleName": null, "email": "", "job": "Driver", "roomContact": "7256", "office": "Accountant General's Office"}, {"firstName": "Prudence", "lastName": "Rwangoga", "middleName": "Ayebazibwe", "email": "", "job": "AC/HR/Treasury", "roomContact": "7273", "office": "Accountant General's Office"}, {"firstName": "Lucy", "lastName": "Acen", "middleName": null, "email": "", "job": "PHRO", "roomContact": "7296", "office": "Accountant General's Office"}, {"firstName": "Lindah", "lastName": "Nanziri", "middleName": null, "email": "", "job": "HRO", "roomContact": "7924", "office": "Accountant General's Office"}, {"firstName": "Nakyama", "lastName": "Bridget", "middleName": null, "email": "", "job": "SHRO", "roomContact": "7924", "office": "Accountant General's Office"}, {"firstName": "Owuma", "lastName": "Gilbert", "middleName": null, "email": "", "job": "Research Officer", "roomContact": "7924", "office": "Accountant General's Office"}, {"firstName": "Agnes", "lastName": "Nayiga", "middleName": null, "email": "", "job": "Records Assistant", "roomContact": "7924", "office": "Accountant General's Office"}, {"firstName": "Margrate", "lastName": "Apio", "middleName": null, "email": "", "job": "Accounts Assistant", "roomContact": "7924", "office": "Accountant General's Office"}, {"firstName": "Jennifer", "lastName": "Rugunda", "middleName": "Nyakato", "email": "", "job": "Asst. Records Officer", "roomContact": "7373", "office": "Accountant General's Office"}, {"firstName": "Steven", "lastName": "Medo", "middleName": "Godfrey", "email": "", "job": "Records Assistant", "roomContact": "7373", "office": "Accountant General's Office"}, {"firstName": "Agnes", "lastName": "Naiga", "middleName": null, "email": "", "job": "Records Assistant", "roomContact": "7373", "office": "Accountant General's Office"}, {"firstName": "Modo", "lastName": "Ruth", "middleName": null, "email": "", "job": "Sen. Records Officer", "roomContact": "7355", "office": "Accountant General's Office"}, {"firstName": "Jackline", "lastName": "Adong", "middleName": null, "email": "", "job": "Office Attendant", "roomContact": "7355", "office": "Accountant General's Office"}, {"firstName": "Joyce", "lastName": "Acen", "middleName": null, "email": "", "job": "Librarian", "roomContact": "7299", "office": "Accountant General's Office"}, {"firstName": "Mariam", "lastName": "Mukabya", "middleName": null, "email": "", "job": "Asst. Librarian", "roomContact": "7299", "office": "Accountant General's Office"}, {"firstName": "Catherine", "lastName": "Kyomugisha", "middleName": null, "email": "", "job": "Asst. Librarian", "roomContact": "7299", "office": "Accountant General's Office"}, {"firstName": "Wilberforce", "lastName": "Wandera", "middleName": null, "email": "", "job": "Office Attendant", "roomContact": "7298", "office": "Accountant General's Office"}, {"firstName": "Cecilia", "lastName": "Nakiwala", "middleName": null, "email": "", "job": "Office Attendant", "roomContact": "7299", "office": "Accountant General's Office"}, {"firstName": "Livingstone", "lastName": "Kiwanuka", "middleName": null, "email": "", "job": "Accounts Asst./Cashier", "roomContact": "7243", "office": "Financial Management Services"}, {"firstName": "Betty", "lastName": "Namayanja", "middleName": null, "email": "", "job": "Personal Secretary", "roomContact": "7252", "office": "Financial Management Services"}, {"firstName": "Maris", "lastName": "Wanyera", "middleName": null, "email": "", "job": "Ag.Dir./DCP", "roomContact": "7162", "office": "Debt And Cash Policy"}, {"firstName": "Slyvia", "lastName": "Ahimbisibwe", "middleName": null, "email": "", "job": "Sec/Dir.DCP", "roomContact": "7314", "office": "Debt And Cash Policy"}, {"firstName": "Florence", "lastName": "Nabinfa", "middleName": null, "email": "", "job": "Office Attendant", "roomContact": "7314", "office": "Debt And Cash Policy"}, {"firstName": "Abidat", "lastName": "Cherotich", "middleName": null, "email": "", "job": "Office Attendant", "roomContact": "7314", "office": "Debt And Cash Policy"}, {"firstName": "Robert", "lastName": "Okudi", "middleName": null, "email": "", "job": "Ag.Comm/CPD", "roomContact": "7266", "office": "Cash Policy Department"}, {"firstName": "David", "lastName": "Wamai", "middleName": null, "email": "", "job": "AC/Cash Policy", "roomContact": "7306", "office": "Cash Policy Department"}, {"firstName": "Doreen", "lastName": "Kabejja", "middleName": null, "email": "", "job": "Economist", "roomContact": "7330", "office": "Cash Policy Department"}, {"firstName": "Rehema", "lastName": "Nassazi", "middleName": null, "email": "", "job": "Senior Statician", "roomContact": "7330", "office": "Cash Policy Department"}, {"firstName": "Joseph", "lastName": "Ahimbisibwe", "middleName": null, "email": "", "job": "Economist", "roomContact": "7276", "office": "Cash Policy Department"}, {"firstName": "Robert", "lastName": "Matsiko", "middleName": null, "email": "", "job": "Economist", "roomContact": "7276", "office": "Cash Policy Department"}, {"firstName": "Clives", "lastName": "Ainebyona", "middleName": null, "email": "", "job": "Economist", "roomContact": "7310", "office": "Cash Policy Department"}, {"firstName": "Ferdinand", "lastName": "Tumwebaze", "middleName": null, "email": "", "job": "IT Support Officer/DARC", "roomContact": "7123", "office": "Cash Policy Department"}, {"firstName": "Jane", "lastName": "Mirembe", "middleName": null, "email": "", "job": "Secretary/CPD", "roomContact": "7471", "office": "Cash Policy Department"}, {"firstName": "Douglas", "lastName": "Nakabago", "middleName": "Sanon", "email": "", "job": "Office Attendant", "roomContact": "7312", "office": "Cash Policy Department"}, {"firstName": "Anold", "lastName": "Dhatemwa", "middleName": "Geoffrey", "email": "", "job": "Commissioner", "roomContact": "7279", "office": "Debt Policy Issurance & Department"}, {"firstName": "Zerida", "lastName": "Zigiti", "middleName": null, "email": "", "job": "AC/DPID", "roomContact": "7114", "office": "Debt Policy Issurance & Department"}, {"firstName": "Simon", "lastName": "Opolot", "middleName": "Peter", "email": "", "job": "Principal Economist", "roomContact": "7310", "office": "Debt Policy Issurance & Department"}, {"firstName": "Joy", "lastName": "Gessa", "middleName": null, "email": "", "job": "Senior Economist", "roomContact": "7310", "office": "Debt Policy Issurance & Department"}, {"firstName": "Daphine", "lastName": "Rutazaana", "middleName": null, "email": "", "job": "Principal Economist", "roomContact": "7282", "office": "Debt Policy Issurance & Department"}, {"firstName": "Samson", "lastName": "Muwanguzi", "middleName": null, "email": "", "job": "Senior Economist", "roomContact": "7282", "office": "Debt Policy Issurance & Department"}, {"firstName": "Menno", "lastName": "Ven", "middleName": null, "email": "", "job": "Senior Economist", "roomContact": "7283", "office": "Debt Policy Issurance & Department"}, {"firstName": "Christine", "lastName": "Nakazibwe", "middleName": null, "email": "", "job": "Senior Statician", "roomContact": "7313", "office": "Debt Policy Issurance & Department"}, {"firstName": "Brian", "lastName": "Kanzira", "middleName": null, "email": "", "job": "Senior Economist", "roomContact": "7313", "office": "Debt Policy Issurance & Department"}, {"firstName": "Doreen", "lastName": "Mutoni", "middleName": null, "email": "", "job": "Economist", "roomContact": "7466", "office": "Debt Policy Issurance & Department"}, {"firstName": "Gerald", "lastName": "Uchamgiu", "middleName": null, "email": "", "job": "Economist", "roomContact": "7466", "office": "Debt Policy Issurance & Department"}, {"firstName": "Michael", "lastName": "Ogole", "middleName": null, "email": "", "job": "Economist", "roomContact": "7466", "office": "Debt Policy Issurance & Department"}, {"firstName": "Wiajik", "lastName": "Grace", "middleName": null, "email": "", "job": "Secretary", "roomContact": "7469", "office": "Debt Policy Issurance & Department"}, {"firstName": "Betty", "lastName": "Namuli", "middleName": null, "email": "", "job": "Office Attendant", "roomContact": "7469", "office": "Debt Policy Issurance & Department"}, {"firstName": "Jenipher", "lastName": "Muhuruzi", "middleName": null, "email": "", "job": "Ag. Dir/ TSAM", "roomContact": "7112", "office": "Treasury Services & Assets Management"}, {"firstName": "Margaret", "lastName": "Basaza", "middleName": "Mbona", "email": "", "job": "Sec/TSAM", "roomContact": "7312", "office": "Treasury Services & Assets Management"}, {"firstName": "Mubaraka", "lastName": "Nasamba", "middleName": null, "email": "", "job": "Ag. AC/TSD", "roomContact": "7286", "office": "Treasury Services"}, {"firstName": "Betty", "lastName": "Kirya", "middleName": "N.", "email": "", "job": "Secretary", "roomContact": "7280", "office": "Treasury Services"}, {"firstName": "Nanteza", "lastName": "Hadija", "middleName": null, "email": "", "job": "Office Attendant", "roomContact": "7280", "office": "Treasury Services"}, {"firstName": "Maurine", "lastName": "Kiconco", "middleName": null, "email": "", "job": "Accountant", "roomContact": "7280", "office": "Treasury Services"}, {"firstName": "Libert", "lastName": "Baluku", "middleName": null, "email": "", "job": "Accountant", "roomContact": "7285", "office": "Treasury Services"}, {"firstName": "Peter", "lastName": "Mutaawe", "middleName": null, "email": "", "job": "Accountant", "roomContact": "7461", "office": "Treasury Services"}, {"firstName": "Apophia", "lastName": "Akampurira", "middleName": null, "email": "", "job": "Accountant", "roomContact": "7461", "office": "Treasury Services"}, {"firstName": "Immaculate", "lastName": "Nabayinda", "middleName": "M", "email": "", "job": "Accountant", "roomContact": "7278", "office": "Treasury Services"}, {"firstName": "Hope", "lastName": "Nesiho", "middleName": "Dombo", "email": "", "job": "Accountant", "roomContact": "7278", "office": "Treasury Services"}, {"firstName": "Ronald", "lastName": "Turihoahabwe", "middleName": null, "email": "", "job": "Accountant", "roomContact": "7447", "office": "Treasury Services"}, {"firstName": "Daniel", "lastName": "Kigenyi", "middleName": null, "email": "", "job": "Ag. Comm/AMD", "roomContact": "7268", "office": "Assets Management"}, {"firstName": "Pedson", "lastName": "Twesigomwe", "middleName": null, "email": "", "job": "Prin. Accountant", "roomContact": "7431", "office": "Assets Management"}, {"firstName": "Agnes", "lastName": "Komugisha", "middleName": null, "email": "", "job": "Secretary", "roomContact": "7265", "office": "Assets Management"}, {"firstName": "Nanteza", "lastName": "Hadijah", "middleName": null, "email": "", "job": "Office Attendant", "roomContact": "7265", "office": "Assets Management"}, {"firstName": "Irene", "lastName": "Nakanwagi", "middleName": null, "email": "", "job": "Accountant/ AMD", "roomContact": "7265", "office": "Assets Management"}, {"firstName": "Tabaro", "lastName": "Richard", "middleName": null, "email": "", "job": "Principal Accountant", "roomContact": "7257", "office": "Assets Management"}, {"firstName": "Godfrey", "lastName": "Luggya", "middleName": "Makedi", "email": "", "job": "Accountant", "roomContact": "7438", "office": "Assets Management"}, {"firstName": "Peter", "lastName": "Sekabanja", "middleName": "Mutawe", "email": "", "job": "Accountant", "roomContact": "7280", "office": "Assets Management"}, {"firstName": "Chris", "lastName": "Otim", "middleName": null, "email": "", "job": "Accountant", "roomContact": "7264", "office": "Assets Management"}, {"firstName": "Titus", "lastName": "Watmon", "middleName": null, "email": "", "job": "Office Attendant", "roomContact": "7252", "office": "Assets Management"}, {"firstName": "Lamula", "lastName": "Nalunkuma", "middleName": null, "email": "", "job": "Accountant", "roomContact": "7264", "office": "Assets Management"}, {"firstName": "Nsubuga", "lastName": "Mayengo", "middleName": "Yusuf", "email": "", "job": "Accountant", "roomContact": "7264/7392", "office": "Assets Management"}, {"firstName": "Ann", "lastName": "Natamba", "middleName": null, "email": "", "job": "Accountant", "roomContact": "7264/7392", "office": "Assets Management"}, {"firstName": "SimonMakuyi", "lastName": "SimonMakuyi", "middleName": null, "email": "", "job": "Accountant", "roomContact": "7265", "office": "Assets Management"}, {"firstName": "Susan", "lastName": "Ashaba", "middleName": null, "email": "", "job": "Accountant", "roomContact": "7264", "office": "Assets Management"}, {"firstName": "Kanamwangi", "lastName": "Nicholas", "middleName": null, "email": "", "job": "Accountant", "roomContact": "7264/7392", "office": "Assets Management"}, {"firstName": "Harriet", "lastName": "Namirembe", "middleName": null, "email": "", "job": "Accountant/NAV Support", "roomContact": "7444", "office": "Assets Management"}, {"firstName": "David", "lastName": "Kiyingi", "middleName": "Nyimbwa", "email": "", "job": "Ag.Comm/Pr. Policy", "roomContact": "7342", "office": "Procurement Policy And Management Department"}, {"firstName": "Muhammed", "lastName": "Segonga", "middleName": null, "email": "", "job": "Prin.Procurement officer", "roomContact": "7300", "office": "Procurement Policy And Management Department"}, {"firstName": "Alfred", "lastName": "Lapyem", "middleName": null, "email": "", "job": "Princ.Procurement officer", "roomContact": "7301", "office": "Procurement Policy And Management Department"}, {"firstName": "Daniel", "lastName": "Olero", "middleName": "Ongom", "email": "", "job": "Research Assistant", "roomContact": "7270", "office": "Procurement Policy And Management Department"}, {"firstName": "Proscovia", "lastName": "Nakyeyune", "middleName": null, "email": "", "job": "Personal Secretary", "roomContact": "7363", "office": "Procurement Policy And Management Department"}, {"firstName": "Asiimwe", "lastName": "Immaculate", "middleName": null, "email": "", "job": "Procurement officer", "roomContact": "7270", "office": "Procurement Policy And Management Department"}, {"firstName": "Ritah", "lastName": "Twikirize", "middleName": null, "email": "", "job": "Office Attendant", "roomContact": "7363", "office": "Procurement Policy And Management Department"}, {"firstName": "Betty", "lastName": "Namayanja", "middleName": null, "email": "", "job": "Personal Secretary", "roomContact": "7252", "office": "Financial Management Services"}, {"firstName": "Livingstone", "lastName": "Kiwanuka", "middleName": null, "email": "", "job": "Accounts Asst./Cashier", "roomContact": "7243", "office": "Financial Management Services"}, {"firstName": "Tembo", "lastName": "Hafsa", "middleName": null, "email": "", "job": "Accountant", "roomContact": "7472", "office": "Financial Management Systems"}, {"firstName": "Tracy", "lastName": "Atuhirwe", "middleName": null, "email": "", "job": "Accountant", "roomContact": "7472", "office": "Financial Management Systems"}, {"firstName": "Edward", "lastName": "Ekonga", "middleName": null, "email": "", "job": "Accountant", "roomContact": "7472", "office": "Financial Management Systems"}, {"firstName": "Amis", "lastName": "Musisi", "middleName": null, "email": "", "job": "Accountant", "roomContact": "7472", "office": "Financial Management Systems"}, {"firstName": "Ivy", "lastName": "Nantumbwe", "middleName": null, "email": "", "job": "Accountant", "roomContact": "7472", "office": "Financial Management Systems"}, {"firstName": "Matia", "lastName": "Mulumba", "middleName": null, "email": "", "job": "Accountant", "roomContact": "7297", "office": "Financial Management Systems"}, {"firstName": "Aida", "lastName": "Emadit", "middleName": null, "email": "", "job": "Accountant", "roomContact": "7297", "office": "Financial Management Systems"}, {"firstName": "Alexandra", "lastName": "Kalenda", "middleName": null, "email": "", "job": "Accountant", "roomContact": "7297", "office": "Financial Management Systems"}, {"firstName": "Naome", "lastName": "Katafiire", "middleName": null, "email": "", "job": "Data contoller", "roomContact": "7272", "office": "Treasury Services Center"}, {"firstName": "Joseph", "lastName": "Openy", "middleName": null, "email": "", "job": "Office Attendant", "roomContact": "7272", "office": "Treasury Services Center"}, {"firstName": "Fay", "lastName": "Ninsiima", "middleName": null, "email": "", "job": "IFMS Systems Officer", "roomContact": "7305", "office": "Treasury Services Center"}, {"firstName": "Nabuwati", "lastName": "Babirye", "middleName": null, "email": "", "job": "SA/Programmer", "roomContact": "7440", "office": "Treasury Services Center"}, {"firstName": "Help", "lastName": "Desk", "middleName": null, "email": "", "job": "IFMS", "roomContact": "7305", "office": "Treasury Services Center"}, {"firstName": "Ambrose", "lastName": "Promise", "middleName": null, "email": "", "job": "Ag. Comm", "roomContact": "7345", "office": "Public Sector Accounts Department"}, {"firstName": "Martha", "lastName": "Byekwaso", "middleName": null, "email": "", "job": "Secretary", "roomContact": "7267", "office": "Public Sector Accounts Department"}, {"firstName": "Aziz", "lastName": "Ssetaala", "middleName": null, "email": "", "job": "Ag. AC/PSAD", "roomContact": "7269", "office": "Public Sector Accounts Department"}, {"firstName": "Yvone", "lastName": "Kabyanga", "middleName": null, "email": "", "job": "Accountant", "roomContact": "7349", "office": "Public Sector Accounts Department"}, {"firstName": "Flavia", "lastName": "Mbasooka", "middleName": "Bukko", "email": "", "job": "Accountant", "roomContact": "7349", "office": "Public Sector Accounts Department"}, {"firstName": "Douglas", "lastName": "Sseremba", "middleName": null, "email": "", "job": "Accountant", "roomContact": "7344", "office": "Public Sector Accounts Department"}, {"firstName": "Steven", "lastName": "Bameka", "middleName": null, "email": "", "job": "Accountant", "roomContact": "7344", "office": "Public Sector Accounts Department"}, {"firstName": "Andrew", "lastName": "Arinaitwe", "middleName": null, "email": "", "job": "Accountant", "roomContact": "7347", "office": "Public Sector Accounts Department"}, {"firstName": "Barbara", "lastName": "Rhoda", "middleName": null, "email": "", "job": "Accountant", "roomContact": "7347", "office": "Public Sector Accounts Department"}, {"firstName": "Onesmus", "lastName": "Akampamya", "middleName": null, "email": "", "job": "Accountant", "roomContact": "7346", "office": "Public Sector Accounts Department"}, {"firstName": "Barbara", "lastName": "Nakintu", "middleName": null, "email": "", "job": "Accountant", "roomContact": "7458", "office": "Public Sector Accounts Department"}, {"firstName": "Paul", "lastName": "Barasa", "middleName": "Dan", "email": "", "job": "Accountant", "roomContact": "7346", "office": "Public Sector Accounts Department"}, {"firstName": "Melanie", "lastName": "Nansubuga", "middleName": "Kizito", "email": "", "job": "Accountant", "roomContact": "7346", "office": "Public Sector Accounts Department"}, {"firstName": "Elizabeth", "lastName": "Tushemerirwe", "middleName": null, "email": "", "job": "Accountant", "roomContact": "7346", "office": "Public Sector Accounts Department"}, {"firstName": "Apolo", "lastName": "Fiona", "middleName": null, "email": "", "job": "Accountant", "roomContact": "7346", "office": "Public Sector Accounts Department"}, {"firstName": "Innocent", "lastName": "Ainebyona", "middleName": null, "email": "", "job": "Accountant", "roomContact": "7346", "office": "Public Sector Accounts Department"}, {"firstName": "Maria", "lastName": "Nabakooza", "middleName": null, "email": "", "job": "Records Asst.", "roomContact": "7267", "office": "Public Sector Accounts Department"}, {"firstName": "Evas", "lastName": "Musiime", "middleName": null, "email": "", "job": "Office Attendant", "roomContact": "7267", "office": "Public Sector Accounts Department"}, {"firstName": "Ronald", "lastName": "Atuhairwe", "middleName": null, "email": "", "job": "Systems Accountant", "roomContact": "7386", "office": "Systems Accountants Datacenter"}, {"firstName": "Acheng", "lastName": "Enid", "middleName": null, "email": "", "job": "Systems Accountant", "roomContact": "7386", "office": "Systems Accountants Datacenter"}, {"firstName": "Macreen", "lastName": "Kyomuhangi", "middleName": null, "email": "", "job": "Systems Accountant", "roomContact": "7386", "office": "Systems Accountants Datacenter"}, {"firstName": "Keneth", "lastName": "Mugisha", "middleName": null, "email": "", "job": "Systems Accountant", "roomContact": "7386", "office": "Systems Accountants Datacenter"}, {"firstName": "Emmanuel", "lastName": "Kiwanuka", "middleName": null, "email": "", "job": "Systems Accountant", "roomContact": "7386", "office": "Systems Accountants Datacenter"}, {"firstName": "Gloria", "lastName": "Kansiime", "middleName": null, "email": "", "job": "Systems Accountant", "roomContact": "7388", "office": "Systems Accountants Datacenter"}, {"firstName": "Juliet", "lastName": "Sseraabidde", "middleName": null, "email": "", "job": "Systems Accountant", "roomContact": "7387", "office": "Systems Accountants Datacenter"}, {"firstName": "Akello", "lastName": "Kimberly", "middleName": null, "email": "", "job": "Systems Accountant", "roomContact": "7388", "office": "Systems Accountants Datacenter"}, {"firstName": "Akello", "lastName": "Ivy", "middleName": null, "email": "", "job": "Systems Accountant", "roomContact": "7387", "office": "Systems Accountants Datacenter"}, {"firstName": "Job", "lastName": "Mabuya", "middleName": null, "email": "", "job": "Systems Accountant", "roomContact": "7387", "office": "Systems Accountants Datacenter"}, {"firstName": "Joseph", "lastName": "Mwesigwa", "middleName": null, "email": "", "job": "Systems Accountant", "roomContact": "7387", "office": "Systems Accountants Datacenter"}, {"firstName": "Racheal", "lastName": "Kabagenyi", "middleName": null, "email": "", "job": "Systems Accountant", "roomContact": "7387", "office": "Systems Accountants Datacenter"}, {"firstName": "Francis", "lastName": "Jenalist", "middleName": null, "email": "", "job": "Systems Accountant", "roomContact": "7387", "office": "Systems Accountants Datacenter"}, {"firstName": "Maureen", "lastName": "Katushabe", "middleName": null, "email": "", "job": "Systems Accountant", "roomContact": "7387", "office": "Systems Accountants Datacenter"}, {"firstName": "Stephen", "lastName": "Ojiambo", "middleName": null, "email": "", "job": "Commissioner", "roomContact": "7118", "office": "Treasury Inspectorate & Policy"}, {"firstName": "Okwakol", "lastName": "Micheal", "middleName": null, "email": "", "job": "Asst Commisioner", "roomContact": "7295", "office": "Treasury Inspectorate & Policy"}, {"firstName": "Muhumuza", "lastName": "Andrew", "middleName": null, "email": "", "job": "Accountant", "roomContact": "7423", "office": "Treasury Inspectorate & Policy"}, {"firstName": "Baraka", "lastName": "Albina", "middleName": null, "email": "", "job": "Personal Secretary", "roomContact": "7258", "office": "Treasury Inspectorate & Policy"}, {"firstName": "Sarah", "lastName": "Nasiige", "middleName": null, "email": "", "job": "Office Attendant", "roomContact": "7258", "office": "Treasury Inspectorate & Policy"}, {"firstName": "Julius", "lastName": "Okello", "middleName": null, "email": "", "job": "Office Attendant", "roomContact": "7258", "office": "Treasury Inspectorate & Policy"}, {"firstName": "Deo", "lastName": "Lutaaya", "middleName": null, "email": "", "job": "Accountant", "roomContact": "7274", "office": "Treasury Inspectorate & Policy"}, {"firstName": "Jacob", "lastName": "Kabigumira", "middleName": null, "email": "", "job": "Accountant", "roomContact": "7274", "office": "Treasury Inspectorate & Policy"}, {"firstName": "Amina", "lastName": "Wanjuzi", "middleName": null, "email": "", "job": "Research Assistant", "roomContact": "7915", "office": "Treasury Inspectorate & Policy"}, {"firstName": "Joyce", "lastName": "Aceng", "middleName": null, "email": "", "job": "Librarian", "roomContact": "7299", "office": "Treasury Inspectorate & Policy"}, {"firstName": "Cecilia", "lastName": "Nakiwala", "middleName": null, "email": "", "job": "Library Attendant", "roomContact": "7299", "office": "Treasury Inspectorate & Policy"}, {"firstName": "Catherine", "lastName": "Kyomugisha", "middleName": null, "email": "", "job": "Assistant Librarian", "roomContact": "7299", "office": "Treasury Inspectorate & Policy"}, {"firstName": "Miriam", "lastName": "Mukabya", "middleName": null, "email": "", "job": "Assistant Librarian", "roomContact": "7299", "office": "Treasury Inspectorate & Policy"}, {"firstName": "Augustine", "lastName": "Kalule", "middleName": null, "email": "", "job": "Accountant", "roomContact": "7262/7385", "office": "Treasury Inspectorate & Policy"}, {"firstName": "Emmanuel", "lastName": "Katongole", "middleName": null, "email": "", "job": "Principal Systems Officer", "roomContact": "7281", "office": "Information Technology Office"}, {"firstName": "Paul", "lastName": "Lumala", "middleName": null, "email": "", "job": "Systems Officer / Network", "roomContact": "7927", "office": "Information Technology Office"}, {"firstName": "Daphine", "lastName": "Namulindwa", "middleName": null, "email": "", "job": "Office Attendant", "roomContact": "7927", "office": "Information Technology Office"}, {"firstName": "Mofaht", "lastName": "Masaba", "middleName": "R.", "email": "", "job": "Ag AC/MIS", "roomContact": "7936", "office": "Management Information Systems-MIS/IFMS"}, {"firstName": "Gilbert", "lastName": "Mwesigye", "middleName": null, "email": "", "job": "Systems Officer", "roomContact": "7457", "office": "Management Information Systems-MIS/IFMS"}, {"firstName": "Steven", "lastName": "Barungi", "middleName": null, "email": "", "job": "Consultant/IFMS", "roomContact": "7325", "office": "Management Information Systems-MIS/IFMS"}, {"firstName": "Rogers", "lastName": "Baguma", "middleName": null, "email": "", "job": "IFMS Consultant", "roomContact": "7921", "office": "Management Information Systems-MIS/IFMS"}, {"firstName": "Bernadette", "lastName": "Nakabuye", "middleName": null, "email": "", "job": "IFMS Consultant", "roomContact": "7918", "office": "Management Information Systems-MIS/IFMS"}, {"firstName": "Jenipher", "lastName": "Kiiza", "middleName": null, "email": "", "job": "IFMS Consultant", "roomContact": "7906", "office": "Management Information Systems-MIS/IFMS"}, {"firstName": "Norbert", "lastName": "Okello", "middleName": null, "email": "", "job": "IFMS Consultant", "roomContact": "7938", "office": "Management Information Systems-MIS/IFMS"}, {"firstName": "Erasmus", "lastName": "Sunday", "middleName": null, "email": "", "job": "IFMS Database Admin", "roomContact": "7932", "office": "Management Information Systems-MIS/IFMS"}, {"firstName": "Benjamin", "lastName": "Mwema", "middleName": null, "email": "", "job": "Consultant/IFMS", "roomContact": "7449", "office": "Management Information Systems-MIS/IFMS"}, {"firstName": "Hamis", "lastName": "Musisi", "middleName": null, "email": "", "job": "Office Attendant", "roomContact": "7916", "office": "Management Information Systems-MIS/IFMS"}, {"firstName": "Fred", "lastName": "Okwangale", "middleName": null, "email": "", "job": "IFMS Consultant", "roomContact": "7903", "office": "Management Information Systems-MIS/IFMS"}, {"firstName": "Stella", "lastName": "Olinga", "middleName": null, "email": "", "job": "IT.Officer", "roomContact": "7939", "office": "Management Information Systems-MIS/IFMS"}, {"firstName": "Busulwa", "lastName": "Ronald", "middleName": null, "email": "", "job": "Systems Officer", "roomContact": "7926", "office": "Management Information Systems-MIS/IFMS"}, {"firstName": "Helena", "lastName": "Mpangana", "middleName": null, "email": "", "job": "Systems Officer", "roomContact": "7926", "office": "Management Information Systems-MIS/IFMS"}, {"firstName": "Scarlet", "lastName": "Kabahuma", "middleName": null, "email": "", "job": "Systems Officer", "roomContact": "7305", "office": "Service Desk"}, {"firstName": "Ronald", "lastName": "Etyeku", "middleName": null, "email": "", "job": "IT.Officer", "roomContact": "7926", "office": "Management Information Systems-MIS/IFMS"}, {"firstName": "Saadi", "lastName": "Lubega", "middleName": null, "email": "", "job": "IT.Officer", "roomContact": "7926", "office": "Management Information Systems-MIS/IFMS"}, {"firstName": "Petra", "lastName": "Okot", "middleName": null, "email": "", "job": "SA/Programmer", "roomContact": "7925", "office": "Management Information Systems-MIS/IFMS"}, {"firstName": "Bernard", "lastName": "Wakyaya", "middleName": null, "email": "", "job": "IT.Officer", "roomContact": "7925", "office": "Management Information Systems-MIS/IFMS"}, {"firstName": "Ambrose", "lastName": "Asiimwe", "middleName": null, "email": "", "job": "IT.Officer", "roomContact": "7925", "office": "Management Information Systems-MIS/IFMS"}, {"firstName": "Eric", "lastName": "Gabriel", "middleName": null, "email": "", "job": "IT.Officer", "roomContact": "7925", "office": "Management Information Systems-MIS/IFMS"}, {"firstName": "Samson", "lastName": "Byereeta", "middleName": "L.", "email": "", "job": "SA/Programmer", "roomContact": "7940", "office": "Management Information Systems-MIS/IFMS"}, {"firstName": "Leona", "lastName": "Kwikiriza", "middleName": "Faith", "email": "", "job": "Systems Analyst", "roomContact": "7920", "office": "Management Information Systems-MIS/IFMS"}, {"firstName": "Monica", "lastName": "Mugisha", "middleName": null, "email": "", "job": "SA/Programmer", "roomContact": "7943", "office": "Management Information Systems-MIS/IFMS"}, {"firstName": "Jane", "lastName": "Nyangoma", "middleName": null, "email": "", "job": "Systems Officer", "roomContact": "7419", "office": "Management Information Systems-MIS/IFMS"}, {"firstName": "Charles", "lastName": "Debuas", "middleName": null, "email": "", "job": "Systems Officer", "roomContact": "7467", "office": "Management Information Systems-MIS/IFMS"}, {"firstName": "Tony", "lastName": "Yawe", "middleName": null, "email": "", "job": "Senior IT.Officer/Data Centre", "roomContact": "7934", "office": "Management Information Systems-MIS/IFMS"}, {"firstName": "David", "lastName": "Orech", "middleName": null, "email": "", "job": "System Analysist", "roomContact": "7923", "office": "Management Information Systems-MIS/IFMS"}, {"firstName": "Duncan", "lastName": "Kagulu", "middleName": null, "email": "", "job": "IT.Officer", "roomContact": "7502", "office": "Management Information Systems-MIS/IFMS"}, {"firstName": "Dorothy", "lastName": "Binkiya", "middleName": null, "email": "", "job": "Systems Analyst", "roomContact": "7913", "office": "Management Information Systems-MIS/IFMS"}, {"firstName": "Gilbert", "lastName": "Eriko", "middleName": null, "email": "", "job": "Systems Analyst/DataCenter", "roomContact": "7379", "office": "Management Information Systems-MIS/IFMS"}, {"firstName": "Lydia", "lastName": "Tusingwire", "middleName": null, "email": "", "job": "Sen. Production Officer", "roomContact": "7445", "office": "Management Information Systems-MIS"}, {"firstName": "Fixon", "lastName": "DR.", "middleName": null, "email": "", "job": "Ag. Internal Auditor General", "roomContact": "7116", "office": "Directorate Of Internal Audit"}, {"firstName": "Stephen", "lastName": "Enabu", "middleName": null, "email": "", "job": "Ag.C/Internal Auditor Mgt", "roomContact": "7290", "office": "Directorate Of Internal Audit"}, {"firstName": "Alice", "lastName": "Nangoku", "middleName": null, "email": "", "job": "Ag. AC/Internal Audit", "roomContact": "7292", "office": "Directorate Of Internal Audit"}, {"firstName": "Josephine", "lastName": "Adukut", "middleName": null, "email": "", "job": "Internal Auditor", "roomContact": "7316", "office": "Directorate Of Internal Audit"}, {"firstName": "Moses", "lastName": "Waiswa", "middleName": null, "email": "", "job": "Internal Auditor", "roomContact": "7287", "office": "Directorate Of Internal Audit"}, {"firstName": "Sauba", "lastName": "Mukaliyewujja", "middleName": null, "email": "", "job": "Senior Internal Auditor", "roomContact": "7287", "office": "Directorate Of Internal Audit"}, {"firstName": "Hussen", "lastName": "Isingoma", "middleName": null, "email": "", "job": "Ag.C/Forensic&Risk Advisory", "roomContact": "7319", "office": "Forensics & Risk Management"}, {"firstName": "Paul", "lastName": "Ocheng", "middleName": null, "email": "", "job": "Internal Auditor", "roomContact": "7287/7339", "office": "Forensics & Risk Management"}, {"firstName": "Nanyondo", "lastName": "Betty", "middleName": null, "email": "", "job": "Ag.C/IT&Performance Aud.", "roomContact": "7291", "office": "IT & Performance AUDIT"}, {"firstName": "Samson", "lastName": "Sowate", "middleName": null, "email": "", "job": "AC/Internal Audit", "roomContact": "7316", "office": "IT & Performance AUDIT"}, {"firstName": "Prosper", "lastName": "Twinamatsiko", "middleName": null, "email": "", "job": "Senior Internal Auditor", "roomContact": "7287", "office": "IT & Performance AUDIT"}, {"firstName": "Allan", "lastName": "Ssekitoleko", "middleName": "B.", "email": "", "job": "Internal Auditor", "roomContact": "7287/7339", "office": "IT & Performance AUDIT"}, {"firstName": "Moses", "lastName": "Nkwasibwe", "middleName": null, "email": "", "job": "Internal Auditor", "roomContact": "7294", "office": "IT & Performance AUDIT"}, {"firstName": "Flavia", "lastName": "Mutabule", "middleName": null, "email": "", "job": "Internal Auditor", "roomContact": "7316", "office": "IT & Performance AUDIT"}, {"firstName": "Bob", "lastName": "Kagaba", "middleName": null, "email": "", "job": "Sen.Internal Auditor", "roomContact": "7294", "office": "IT & Performance AUDIT"}, {"firstName": "Martha", "lastName": "Nagadya", "middleName": null, "email": "", "job": "Personal Secretary", "roomContact": "7294", "office": "IT & Performance AUDIT"}, {"firstName": "Tabisa", "lastName": "Akello", "middleName": null, "email": "", "job": "Personal Secretary", "roomContact": "7380", "office": "IT & Performance AUDIT"}, {"firstName": "Sally", "lastName": "Ayeka", "middleName": null, "email": "", "job": "Office Attendant", "roomContact": "7294", "office": "IT & Performance AUDIT"}, {"firstName": "Peter", "lastName": "Dr.", "middleName": "Ngategize", "email": "", "job": "National Coordinator", "roomContact": "7323", "office": "Private Sector Development Unit"}, {"firstName": "Daina", "lastName": "Nannono", "middleName": "M", "email": "", "job": "Legal Regulatory officer", "roomContact": "7188", "office": "Private Sector Development Unit"}, {"firstName": "Sarah", "lastName": "Kabasinguzi", "middleName": null, "email": "", "job": "Competitiveness Analyst/ME", "roomContact": "7302", "office": "Private Sector Development Unit"}, {"firstName": "Mayers", "lastName": "Asiimwe", "middleName": null, "email": "", "job": "Value Chain Analyst", "roomContact": "7302/4234704", "office": "Private Sector Development Unit"}, {"firstName": "Rogers", "lastName": "Kwebangira", "middleName": null, "email": "", "job": "Accountant", "roomContact": "7324", "office": "Private Sector Development Unit"}, {"firstName": "Robert", "lastName": "Wamulimah", "middleName": "Paul", "email": "", "job": "Sen.Competetiveness Analyst", "roomContact": "7288", "office": "Private Sector Development Unit"}, {"firstName": "Richard", "lastName": "Mubiru", "middleName": null, "email": "", "job": "AC/CB &ED", "roomContact": "7304", "office": "Private Sector Development Unit"}, {"firstName": "Helen", "lastName": "Twodo", "middleName": null, "email": "", "job": "Senior Personal Secretary", "roomContact": "7322", "office": "Private Sector Development Unit"}, {"firstName": "Anthony", "lastName": "Bugembe", "middleName": null, "email": "", "job": "Office Attendant", "roomContact": "7322", "office": "Private Sector Development Unit"}, {"firstName": "Ruth", "lastName": "Kato", "middleName": null, "email": "", "job": "Project Cordinator", "roomContact": "7271", "office": "NAO Support Unit"}, {"firstName": "Barbra", "lastName": "Rwomushana", "middleName": null, "email": "", "job": "Finance&Contracts Officer", "roomContact": "7181", "office": "NAO Support Unit"}, {"firstName": "Francis", "lastName": "Okello", "middleName": null, "email": "", "job": "Finance&Admin Assistant", "roomContact": "7180", "office": "NAO Support Unit"}, {"firstName": "Eunice", "lastName": "Kyerabira", "middleName": null, "email": "", "job": "Finance&Contracts Officer", "roomContact": "7326", "office": "NAO Support Unit"}, {"firstName": "Anthony", "lastName": "Mwanje", "middleName": "Kintu", "email": "", "job": "Sector Coordinator", "roomContact": "7508", "office": "Accountability Sector Secretariat"}, {"firstName": "Geoffrey", "lastName": "Kakara", "middleName": null, "email": "", "job": "Public Fin. Mgt.Advisor", "roomContact": "7284", "office": "Accountability Sector Secretariat"}, {"firstName": "Specio", "lastName": "Agaba", "middleName": null, "email": "", "job": "Accounts Assistant", "roomContact": "7414", "office": "Accountability Sector Secretariat"}, {"firstName": "Scovia", "lastName": "Kenaga", "middleName": null, "email": "", "job": "Jr. Technical Assistant", "roomContact": "7507", "office": "Accountability Sector Secretariat"}, {"firstName": "Nicodemus", "lastName": "Nayebare", "middleName": null, "email": "", "job": "Jr. Technical Assistant", "roomContact": "7507", "office": "Accountability Sector Secretariat"}, {"firstName": "Brenda", "lastName": "Nantege", "middleName": null, "email": "", "job": "Office Attendant", "roomContact": "7507", "office": "Accountability Sector Secretariat"}, {"firstName": "Gorreti", "lastName": "Kajumba", "middleName": null, "email": "", "job": "Technical Assistant", "roomContact": "7464", "office": "Accountability Sector Secretariat"}, {"firstName": "Anna", "lastName": "Niyonzima", "middleName": null, "email": "", "job": "Administrative Assistant", "roomContact": "7464", "office": "Accountability Sector Secretariat"}, {"firstName": "Betty", "lastName": "Kasimbazi", "middleName": null, "email": "", "job": "Under Secretary /AO", "roomContact": "7108", "office": "Administration"}, {"firstName": "Jolly", "lastName": "Sebacuzi", "middleName": null, "email": "", "job": "Secretary", "roomContact": "7207", "office": "Administration"}, {"firstName": "Margret", "lastName": "Adyero", "middleName": null, "email": "", "job": "Office Attendant", "roomContact": "7207", "office": "Administration"}, {"firstName": "Dr.", "lastName": "Ddamulira", "middleName": null, "email": "", "job": "Principal Assistant Secretary", "roomContact": "7109", "office": "Administration"}, {"firstName": "Rosemary", "lastName": "Guzu", "middleName": null, "email": "", "job": "Secretary/PAS", "roomContact": "7208", "office": "Administration"}, {"firstName": "Elijah", "lastName": "Emapus", "middleName": null, "email": "", "job": "Office Attendant /PAS", "roomContact": "7208", "office": "Administration"}, {"firstName": "Nathan", "lastName": "Dawanah", "middleName": "Gessa", "email": "", "job": "SAS/L/PA(MF)", "roomContact": "7119", "office": "Administration"}, {"firstName": "Diana", "lastName": "Kabagambe", "middleName": null, "email": "", "job": "SAS/G", "roomContact": "7211", "office": "Administration"}, {"firstName": "Ronald", "lastName": "Osekenye", "middleName": null, "email": "", "job": "SAS/TO/PA(P)", "roomContact": "7178", "office": "Administration"}, {"firstName": "Charles", "lastName": "Wasswa", "middleName": "Jude", "email": "", "job": "SAS", "roomContact": "7212", "office": "Administration"}, {"firstName": "Dorcus", "lastName": "Otim", "middleName": null, "email": "", "job": "SAS/PA (Hon. Minister)", "roomContact": "7382", "office": "Administration"}, {"firstName": "Aida", "lastName": "Nanzigwa", "middleName": "Batuusa", "email": "", "job": "SAS/F", "roomContact": "7378", "office": "Administration"}, {"firstName": "Ronald", "lastName": "Kironde", "middleName": null, "email": "", "job": "AS", "roomContact": "7213", "office": "Administration"}, {"firstName": "Maryline", "lastName": "Ogena", "middleName": null, "email": "", "job": "AS", "roomContact": "7214", "office": "Administration"}, {"firstName": "Komugisa", "lastName": "Rosette", "middleName": null, "email": "", "job": "AS", "roomContact": "7214", "office": "Administration"}, {"firstName": "Stephen", "lastName": "Kasangaki", "middleName": null, "email": "", "job": "Commisioner /CPA", "roomContact": "7156", "office": "Cabinent And Parliament Affairs"}, {"firstName": "Miriam", "lastName": "Akol", "middleName": null, "email": "", "job": "Secretary/ CPA", "roomContact": "7127", "office": "Cabinent And Parliament Affairs"}, {"firstName": "Akiki", "lastName": "Tumusiime", "middleName": "Julius", "email": "", "job": "Economist", "roomContact": "7186", "office": "Cabinent And Parliament Affairs"}, {"firstName": "Charles", "lastName": "Ziraba", "middleName": null, "email": "", "job": "AC/HRM/F", "roomContact": "7124", "office": "Human Resource Division"}, {"firstName": "Nelson", "lastName": "Kahandi", "middleName": "E.", "email": "", "job": "PHRO", "roomContact": "7121", "office": "Human Resource Division"}, {"firstName": "Francis", "lastName": "Geneeton", "middleName": "Emitu", "email": "", "job": "SHRO", "roomContact": "7384", "office": "Human Resource Division"}, {"firstName": "Nancy", "lastName": "Nyinomujuni", "middleName": null, "email": "", "job": "Human Resource Officer", "roomContact": "7366", "office": "Human Resource Division"}, {"firstName": "Edward", "lastName": "Mujoba", "middleName": null, "email": "", "job": "HRA", "roomContact": "7366", "office": "Human Resource Division"}, {"firstName": "Gladys", "lastName": "Oyeru", "middleName": null, "email": "", "job": "Pool Stenographer", "roomContact": "7210", "office": "Human Resource Division"}, {"firstName": "AsiyatiNamata", "lastName": "AsiyatiNamata", "middleName": null, "email": "", "job": "Office Attendant", "roomContact": "7210", "office": "Human Resource Division"}, {"firstName": "Patricia", "lastName": "Iga", "middleName": "Nyachwo", "email": "", "job": "Asst Comm/CAD", "roomContact": "7238", "office": "Accounts Division"}, {"firstName": "Francis", "lastName": "Azabo", "middleName": null, "email": "", "job": "Sen. Acct/CAD", "roomContact": "7235", "office": "Accounts Division"}, {"firstName": "Irene", "lastName": "Barasa", "middleName": null, "email": "", "job": "Accountant", "roomContact": "7249", "office": "Accounts Division"}, {"firstName": "Hawah", "lastName": "Kigaaga", "middleName": null, "email": "", "job": "Sen.Personal Secretary", "roomContact": "7215", "office": "Accounts Division"}, {"firstName": "Charles", "lastName": "Mukasa", "middleName": null, "email": "", "job": "Accountant/Exam", "roomContact": "7237", "office": "Accounts Division"}, {"firstName": "Rogers", "lastName": "Oyimo", "middleName": null, "email": "", "job": "Accounts Asst./ Book keeping", "roomContact": "7251", "office": "Accounts Division"}, {"firstName": "Monica", "lastName": "Kitimbo", "middleName": null, "email": "", "job": "Asst.Accountant", "roomContact": "7251", "office": "Accounts Division"}, {"firstName": "Patrick", "lastName": "Katono", "middleName": "Muhairwe", "email": "", "job": "Sen. Acc. Assistant/Salaries", "roomContact": "7236", "office": "Accounts Division"}, {"firstName": "Grace", "lastName": "Cox", "middleName": "Oyera", "email": "", "job": "Accts. Asst/Cashier", "roomContact": "7239", "office": "Accounts Division"}, {"firstName": "Recheal", "lastName": "Asha", "middleName": null, "email": "", "job": "Office Attendant", "roomContact": "7215", "office": "Accounts Division"}, {"firstName": "Evarist", "lastName": "Muhangi", "middleName": null, "email": "", "job": "R/Economist", "roomContact": "7334", "office": "EDPR Office"}, {"firstName": "Tonia", "lastName": "Alado", "middleName": null, "email": "", "job": "R/Economist", "roomContact": "7224", "office": "EDPR Office"}, {"firstName": "Nicholas", "lastName": "Kwehayo", "middleName": null, "email": "", "job": "R/Economist", "roomContact": "7334", "office": "EDPR Office"}, {"firstName": "Swalleh", "lastName": "Senteza", "middleName": null, "email": "", "job": "Ag.AC/Comm", "roomContact": "7240", "office": "Internal Audit Division"}, {"firstName": "Daina", "lastName": "Kiwanuka", "middleName": null, "email": "", "job": "Senior Internal Auditor", "roomContact": "7356", "office": "Internal Audit Division"}, {"firstName": "Bright", "lastName": "Anne", "middleName": null, "email": "", "job": "Internal Auditor", "roomContact": "7261", "office": "Internal Audit Division"}, {"firstName": "Tom", "lastName": "Kamukama", "middleName": null, "email": "", "job": "Internal Auditor", "roomContact": "7261", "office": "Internal Audit Division"}, {"firstName": "Restuta", "lastName": "Nyirasafari", "middleName": null, "email": "", "job": "Stenographer Sec.", "roomContact": "7358", "office": "Internal Audit Division"}, {"firstName": "Sam", "lastName": "Hamba", "middleName": null, "email": "", "job": "Office Attendant", "roomContact": "7358", "office": "Internal Audit Division"}, {"firstName": "Robert", "lastName": "Ochengel", "middleName": "Nelson", "email": "", "job": "Driver", "roomContact": "7358", "office": "Internal Audit Division"}, {"firstName": "Cresent.", "lastName": "Muhumuza", "middleName": "K.", "email": "", "job": "AC/Procurement", "roomContact": "7241", "office": "Procurement Division"}, {"firstName": "John", "lastName": "Nanyumba", "middleName": null, "email": "", "job": "Sen.Proc. Officer", "roomContact": "7336", "office": "Procurement Division"}, {"firstName": "Aminah", "lastName": "Nabulime", "middleName": null, "email": "", "job": "Procurement Offcer", "roomContact": "7435", "office": "Procurement Division"}, {"firstName": "Susan", "lastName": "Nabbuga", "middleName": null, "email": "", "job": "Data Entrant", "roomContact": "7435", "office": "Procurement Division"}, {"firstName": "Jane", "lastName": "Naggayi", "middleName": null, "email": "", "job": "Personal Secretary", "roomContact": "7364", "office": "Procurement Division"}, {"firstName": "Lucy", "lastName": "Bithum", "middleName": null, "email": "", "job": "Senior Personal Secretary", "roomContact": "7216", "office": "Procurement Division"}, {"firstName": "Agnes", "lastName": "Sabano", "middleName": null, "email": "", "job": "Office Attendant", "roomContact": "7216", "office": "Procurement Division"}, {"firstName": "Sarah", "lastName": "Byobona", "middleName": null, "email": "", "job": "Office Attendant", "roomContact": "7216", "office": "Procurement Division"}, {"firstName": "Vicky", "lastName": "Ruth", "middleName": "Malongo", "email": "", "job": "Economist", "roomContact": "7234", "office": "Financial Services Department"}, {"firstName": "Golooba", "lastName": "Kezekia", "middleName": "Lwanga", "email": "", "job": "Senior Economist", "roomContact": "7234", "office": "Financial Services Department"}, {"firstName": "Bosco", "lastName": "Isabirye", "middleName": null, "email": "", "job": "Economist", "roomContact": "7234", "office": "Financial Services Department"}, {"firstName": "Annet", "lastName": "Kajumba", "middleName": null, "email": "", "job": "Graduate Economist", "roomContact": "7234", "office": "Financial Services Department"}, {"firstName": "James", "lastName": "Tibenkana", "middleName": null, "email": "", "job": "PrincipalEconomist", "roomContact": "7242", "office": "Planning Unit"}, {"firstName": "Epiphany", "lastName": "Berocan", "middleName": null, "email": "", "job": "Principal Economist", "roomContact": "7327", "office": "Planning Unit"}, {"firstName": "Annet", "lastName": "Nakalembe", "middleName": null, "email": "", "job": "Economist", "roomContact": "7365", "office": "Planning Unit"}, {"firstName": "Tom", "lastName": "Nyombi", "middleName": null, "email": "", "job": "Economist", "roomContact": "7406", "office": "Planning Unit"}, {"firstName": "Vickie", "lastName": "Kyazze", "middleName": null, "email": "", "job": "Office Attendant", "roomContact": "7406", "office": "Planning Unit"}, {"firstName": "Sandra", "lastName": "Mbambazi", "middleName": null, "email": "", "job": "MO/PSM", "roomContact": "7410", "office": "BMAU Office"}, {"firstName": "Emily", "lastName": "Nohomanya", "middleName": null, "email": "", "job": "MO/Agricultutre", "roomContact": "7410", "office": "BMAU Office"}, {"firstName": "Juliana", "lastName": "Asiimwe", "middleName": "Ivy", "email": "", "job": "MO/ Educ", "roomContact": "7410", "office": "BMAU Office"}, {"firstName": "Florence", "lastName": "Kasuule", "middleName": "Namiwanda", "email": "", "job": "MO/PFM", "roomContact": "7410", "office": "BMAU Office"}, {"firstName": "Lydia", "lastName": "Naula", "middleName": null, "email": "", "job": "MO/Health", "roomContact": "7411", "office": "BMAU Office"}, {"firstName": "Husnah", "lastName": "Matovvu", "middleName": null, "email": "", "job": "MO/Health", "roomContact": "7411", "office": "BMAU Office"}, {"firstName": "Maria", "lastName": "Muzaaki", "middleName": null, "email": "", "job": "Comm officer", "roomContact": "7428", "office": "BMAU Office"}, {"firstName": "Sylvia", "lastName": "Atuhaire", "middleName": null, "email": "", "job": "Communication officer", "roomContact": "7428", "office": "BMAU Office"}, {"firstName": "Esther", "lastName": "Najjuma", "middleName": null, "email": "", "job": "MO /Roads", "roomContact": "7455", "office": "BMAU Office"}, {"firstName": "Sylevester", "lastName": "Kato", "middleName": null, "email": "", "job": "TMO/Health", "roomContact": "7455", "office": "BMAU Office"}, {"firstName": "Doglous", "lastName": "Kisakye", "middleName": null, "email": "", "job": "MO /Roads", "roomContact": "7455", "office": "BMAU Office"}, {"firstName": "Hon.", "lastName": "Kasoro", "middleName": null, "email": "", "job": "MSFPED(MF)", "roomContact": "7351", "office": "Financial Services Department"}, {"firstName": "Lillian", "lastName": "Oguaru", "middleName": null, "email": "", "job": "Prin. Personal Secretary", "roomContact": "7353", "office": "Financial Services Department"}, {"firstName": "Angella", "lastName": "Akiror", "middleName": "Patricia", "email": "", "job": "Steno. Secretary", "roomContact": "7352", "office": "Financial Services Department"}, {"firstName": "John", "lastName": "Kirungi", "middleName": "Byaruhanga", "email": "", "job": "Ag.C/FSD", "roomContact": "7149", "office": "Financial Services Department"}, {"firstName": "Henry", "lastName": "Mbaguta", "middleName": null, "email": "", "job": "AC/FSD", "roomContact": "7169", "office": "Financial Services Department"}, {"firstName": "Musa", "lastName": "Lukwago", "middleName": null, "email": "", "job": "Senior Economist", "roomContact": "7165", "office": "Financial Services Department"}, {"firstName": "Richard", "lastName": "Kirungi", "middleName": "Ndyanabo", "email": "", "job": "Principal Economist", "roomContact": "7408", "office": "Financial Services Department"}, {"firstName": "Avu", "lastName": "Biliku", "middleName": "Elly", "email": "", "job": "Principal Economist", "roomContact": "7409", "office": "Financial Services Department"}, {"firstName": "Lawrence", "lastName": "Kasenge", "middleName": null, "email": "", "job": "Senior Economist", "roomContact": "7372", "office": "Financial Services Department"}, {"firstName": "Gilbert", "lastName": "Onono", "middleName": "Okello", "email": "", "job": "Economist", "roomContact": "7248", "office": "Financial Services Department"}, {"firstName": "Annet", "lastName": "Ireeba", "middleName": null, "email": "", "job": "Senior Economist", "roomContact": "7459", "office": "Financial Services Department"}, {"firstName": "Nelson", "lastName": "Kakye", "middleName": "Mutatiina", "email": "", "job": "Senior Economist", "roomContact": "7398", "office": "Financial Services Department"}, {"firstName": "Jane", "lastName": "Alupo", "middleName": "Grace", "email": "", "job": "Prin. Personal Secretary", "roomContact": "7126", "office": "Financial Services Department"}, {"firstName": "Ritah", "lastName": "Nakagolo", "middleName": null, "email": "", "job": "Pool Steno.Secretary", "roomContact": "7126", "office": "Financial Services Department"}, {"firstName": "Ivan", "lastName": "Mugambagye", "middleName": null, "email": "", "job": "Office Attendant", "roomContact": "7126", "office": "Financial Services Department"}, {"firstName": "Laban", "lastName": "Mbulamuko", "middleName": null, "email": "", "job": "Com/ISSD", "roomContact": "7140", "office": "Infrastructure And Social Services"}, {"firstName": "Florence", "lastName": "Owacha", "middleName": null, "email": "", "job": "Personal Sec/ Com", "roomContact": "7122", "office": "Infrastructure And Social Services"}, {"firstName": "Jennifer", "lastName": "Nansubuga", "middleName": null, "email": "", "job": "Office Attendant", "roomContact": "7122", "office": "Infrastructure And Social Services"}, {"firstName": "Barbra", "lastName": "Nalwoga", "middleName": null, "email": "", "job": "Office Attendant", "roomContact": "7122", "office": "Infrastructure And Social Services"}, {"firstName": "Paul", "lastName": "Mwanja", "middleName": "Patrick", "email": "", "job": "AC/ISSD", "roomContact": "7198", "office": "Infrastructure And Social Services"}, {"firstName": "William", "lastName": "Ndolerire", "middleName": null, "email": "", "job": "AC/ISSD", "roomContact": "7223", "office": "Infrastructure And Social Services"}, {"firstName": "Juliet", "lastName": "Kyokuhaire", "middleName": null, "email": "", "job": "Principal Econ/Health", "roomContact": "7194", "office": "Infrastructure And Social Services"}, {"firstName": "Angela", "lastName": "Matsiko", "middleName": "Rwabutomize", "email": "", "job": "Principal Economist", "roomContact": "7193", "office": "Infrastructure And Social Services"}, {"firstName": "Moses", "lastName": "Ssonko", "middleName": null, "email": "", "job": "Senior Economist", "roomContact": "7193", "office": "Infrastructure And Social Services"}, {"firstName": "Bob", "lastName": "Munene", "middleName": "Banabo", "email": "", "job": "Principal Economist", "roomContact": "7343", "office": "Infrastructure And Social Services"}, {"firstName": "Teddy", "lastName": "Alako", "middleName": null, "email": "", "job": "Senior Economist (educ)", "roomContact": "7206", "office": "Infrastructure And Social Services"}, {"firstName": "Lambart", "lastName": "Olidio", "middleName": null, "email": "", "job": "Senior Economist(Educ)", "roomContact": "7343", "office": "Infrastructure And Social Services"}, {"firstName": "Gideon", "lastName": "Mugisha", "middleName": "Gariyo", "email": "", "job": "Economist", "roomContact": "7371", "office": "Infrastructure And Social Services"}, {"firstName": "Timothy", "lastName": "Namboga", "middleName": null, "email": "", "job": "Economist", "roomContact": "7192", "office": "Infrastructure And Social Services"}, {"firstName": "Mark", "lastName": "Amanya", "middleName": null, "email": "", "job": "Economist", "roomContact": "7192", "office": "Infrastructure And Social Services"}, {"firstName": "Micheal", "lastName": "Kiwanuka", "middleName": "Okot", "email": "", "job": "Senior Economist", "roomContact": "7192", "office": "Infrastructure And Social Services"}, {"firstName": "Olivia", "lastName": "Nassuna", "middleName": null, "email": "", "job": "Economist", "roomContact": "7196", "office": "Infrastructure And Social Services"}, {"firstName": "Harriet", "lastName": "Grace", "middleName": "Acheng", "email": "", "job": "Secretary /ISSD", "roomContact": "7191", "office": "Infrastructure And Social Services"}, {"firstName": "Grace", "lastName": "Wiajik", "middleName": null, "email": "", "job": "Steno. Secretary", "roomContact": "7191", "office": "Infrastructure And Social Services"}, {"firstName": "Morine", "lastName": "Kyazike", "middleName": null, "email": "", "job": "Office Attendant", "roomContact": "7191", "office": "Infrastructure And Social Services"}, {"firstName": "Mathias", "lastName": "Obwapus", "middleName": null, "email": "", "job": "Office Attendant", "roomContact": "7191", "office": "Infrastructure And Social Services"}, {"firstName": "Johnson", "lastName": "Mutesigensi", "middleName": null, "email": "", "job": "Coordinator/REAP", "roomContact": "7905", "office": "FINMAPIII/REAP"}, {"firstName": "Ruth", "lastName": "Komujuni", "middleName": null, "email": "", "job": "Secretary", "roomContact": "7900", "office": "FINMAPIII/REAP"}, {"firstName": "Samuel", "lastName": "Ssozi", "middleName": null, "email": "", "job": "Office Attendant", "roomContact": "7907", "office": "FINMAPIII/REAP"}, {"firstName": "Hellen", "lastName": "Nabafu", "middleName": null, "email": "", "job": "Stores Assistant", "roomContact": "7907", "office": "FINMAPIII/REAP"}, {"firstName": "Paul", "lastName": "Kyama", "middleName": null, "email": "", "job": "Change Mgt &Comm. Specialist", "roomContact": "7901", "office": "FINMAPIII/REAP"}, {"firstName": "Patrick", "lastName": "Kagaba", "middleName": null, "email": "", "job": "Head of Procurement", "roomContact": "7941", "office": "FINMAPIII/REAP"}, {"firstName": "Paul", "lastName": "Ankunda", "middleName": null, "email": "", "job": "Head Finance & Admin", "roomContact": "7950", "office": "FINMAPIII/REAP"}, {"firstName": "Ben", "lastName": "Anywar", "middleName": null, "email": "", "job": "Accounts Officer", "roomContact": "7914", "office": "FINMAPIII/REAP"}, {"firstName": "Winnie", "lastName": "Ainaomugasho", "middleName": null, "email": "", "job": "Accountant", "roomContact": "7910", "office": "FINMAPIII/REAP"}, {"firstName": "Raymond", "lastName": "Jjingo", "middleName": null, "email": "", "job": "Accountant", "roomContact": "7910", "office": "FINMAPIII/REAP"}, {"firstName": "Rachel", "lastName": "Ninsiima", "middleName": null, "email": "", "job": "AdministrationOfficer", "roomContact": "7944", "office": "FINMAPIII/REAP"}, {"firstName": "Nelly", "lastName": "Kirabo", "middleName": null, "email": "", "job": "Accounts Officer", "roomContact": "7945", "office": "FINMAPIII/REAP"}, {"firstName": "Lawrence", "lastName": "Sekyewa", "middleName": null, "email": "", "job": "Sen. Accountant", "roomContact": "7931", "office": "FINMAPIII/REAP"}, {"firstName": "Esther", "lastName": "Owor", "middleName": "Akullo", "email": "", "job": "Head Planning, M&E", "roomContact": "7949", "office": "FINMAPIII/REAP"}, {"firstName": "Yusuf", "lastName": "Mawanda", "middleName": null, "email": "", "job": "Sen. Admin", "roomContact": "7947", "office": "FINMAPIII/REAP"}, {"firstName": "Emmanuel", "lastName": "Mugabi", "middleName": null, "email": "", "job": "Sen M&E Officer", "roomContact": "7902", "office": "FINMAPIII/REAP"}, {"firstName": "Conrad", "lastName": "Kahiima", "middleName": null, "email": "", "job": "Sen M&E Officer", "roomContact": "7948", "office": "FINMAPIII/REAP"}, {"firstName": "Doreen", "lastName": "Muheru", "middleName": null, "email": "", "job": "M&E Officer", "roomContact": "7942", "office": "FINMAPIII/REAP"}, {"firstName": "Daphine", "lastName": "Nyakaisiki", "middleName": null, "email": "", "job": "Procurement Officer", "roomContact": "7904", "office": "FINMAPIII/REAP"}, {"firstName": "Daniel", "lastName": "Murungi", "middleName": null, "email": "", "job": "Senior Procurement Officer", "roomContact": "7946", "office": "FINMAPIII/REAP"}, {"firstName": "Sarah", "lastName": "Alinda", "middleName": "Brenda", "email": "", "job": "Senior Procurement Officer", "roomContact": "7928", "office": "FINMAPIII/REAP"}, {"firstName": "Annet", "lastName": "Arinaitwe", "middleName": null, "email": "", "job": "Procurement Officer", "roomContact": "7911", "office": "FINMAPIII/REAP"}, {"firstName": "Margaret", "lastName": "Kakande", "middleName": null, "email": "", "job": "Head/BMAU", "roomContact": "7202", "office": "BMAU"}, {"firstName": "Rosetti", "lastName": "Nayenga", "middleName": "Nabumba", "email": "", "job": "Dep. Head/BMAU", "roomContact": "7203", "office": "BMAU"}, {"firstName": "Allan", "lastName": "Gitta", "middleName": null, "email": "", "job": "Finance Manager", "roomContact": "7204", "office": "BMAU"}, {"firstName": "Annette", "lastName": "Nansubuga", "middleName": "Sherina", "email": "", "job": "Administrator", "roomContact": "7250", "office": "BMAU"}, {"firstName": "Aber", "lastName": "Beatrice", "middleName": null, "email": "", "job": "Office Attendant", "roomContact": "7250", "office": "BMAU"}, {"firstName": "Jesca", "lastName": "Nakabiri", "middleName": null, "email": "", "job": "Office Attendant", "roomContact": "7250", "office": "BMAU"}, {"firstName": "Elasu", "lastName": "Andrew", "middleName": null, "email": "", "job": "Office Attendant", "roomContact": "7250", "office": "BMAU"}, {"firstName": "Micheal", "lastName": "Aliyo", "middleName": "Barnabas", "email": "", "job": "Prin.Economist /Works & ICT", "roomContact": "7500", "office": "Uganda-Growth DANIDA Programe"}, {"firstName": "Titus", "lastName": "Kajura", "middleName": null, "email": "", "job": "Senior Economist", "roomContact": "7443", "office": "Uganda-Growth DANIDA Programe"}, {"firstName": "Isabella", "lastName": "Mulisa", "middleName": null, "email": "", "job": "Excutive Asst (U-Growth)", "roomContact": "7453", "office": "Uganda-Growth DANIDA Programe"}, {"firstName": "EricSewanyana", "lastName": "EricSewanyana", "middleName": null, "email": "", "job": "M &E Officer/Danida", "roomContact": "7185", "office": "Uganda-Growth DANIDA Programe"}, {"firstName": "Derrick", "lastName": "Kaswabuli", "middleName": null, "email": "", "job": "Office Attendant", "roomContact": "7453", "office": "Uganda-Growth DANIDA Programe"}, {"firstName": "Ian", "lastName": "Mugizi", "middleName": null, "email": "", "job": "Economist/ Works/ICT", "roomContact": "7189", "office": "Uganda-Growth DANIDA Programe"}, {"firstName": "Simon", "lastName": "Ssenyonga", "middleName": "Peter", "email": "", "job": "Fin/Accts(U-Growth)", "roomContact": "7189", "office": "Uganda-Growth DANIDA Programe"}, {"firstName": "Vivian", "lastName": "Tumwebaze", "middleName": null, "email": "", "job": "Economist Works/ICT", "roomContact": "7189", "office": "Uganda-Growth DANIDA Programe"}, {"firstName": "Janat", "lastName": "Nankya", "middleName": "Sanyu", "email": "", "job": "Economist", "roomContact": "7189", "office": "Uganda-Growth DANIDA Programe"}, {"firstName": "Brenda", "lastName": "Nantumbwe", "middleName": null, "email": "", "job": "Economist", "roomContact": "7189", "office": "Uganda-Growth DANIDA Programe"}, {"firstName": "Pauline", "lastName": "Akidi", "middleName": null, "email": "", "job": "Principal Economist/DARC", "roomContact": "7184", "office": "Uganda-Growth DANIDA Programe"}, {"firstName": "Hajime", "lastName": "Onishi", "middleName": null, "email": "", "job": "Loan Advisor(ODA) /DARC", "roomContact": "7417", "office": "Uganda-Growth DANIDA Programe"}, {"firstName": "Gennaro", "lastName": "Volpe", "middleName": null, "email": "", "job": "NAO Advisor", "roomContact": "7416", "office": "Uganda-Growth DANIDA Programe"}, {"firstName": "Ronald", "lastName": "Kintu", "middleName": null, "email": "", "job": "IT Support Officer", "roomContact": "7416", "office": "Uganda-Growth DANIDA Programe"}, {"firstName": "Fred", "lastName": "Twesiime", "middleName": null, "email": "", "job": "Ag. Com /DARC", "roomContact": "7183", "office": "Development Assisstance & Regional Cooperation"}, {"firstName": "Juvenal", "lastName": "Muhumuza", "middleName": "Ntakyo", "email": "", "job": "Ag. AC/DARC", "roomContact": "7415", "office": "Development Assisstance & Regional Cooperation"}, {"firstName": "Mariam", "lastName": "Kiggundu", "middleName": null, "email": "", "job": "Economist", "roomContact": "7354", "office": "Development Assisstance & Regional Cooperation"}, {"firstName": "Isaac", "lastName": "Katabalwa", "middleName": null, "email": "", "job": "Economist", "roomContact": "7161", "office": "Development Assisstance & Regional Cooperation"}, {"firstName": "Wahab", "lastName": "Sessimba", "middleName": null, "email": "", "job": "Senior Economist", "roomContact": "7354", "office": "Development Assisstance & Regional Cooperation"}, {"firstName": "Ester", "lastName": "Asiimwe", "middleName": null, "email": "", "job": "Economist", "roomContact": "7354", "office": "Development Assisstance & Regional Cooperation"}, {"firstName": "Samson", "lastName": "Muwanguzi", "middleName": null, "email": "", "job": "Senior Economist", "roomContact": "7465", "office": "Development Assisstance & Regional Cooperation"}, {"firstName": "Azizah", "lastName": "Nabitalo", "middleName": null, "email": "", "job": "Senior Economist", "roomContact": "7110", "office": "Development Assisstance & Regional Cooperation"}, {"firstName": "Collins", "lastName": "Ishmwe", "middleName": "Hebert", "email": "", "job": "Senior Economist", "roomContact": "7383", "office": "Development Assisstance & Regional Cooperation"}, {"firstName": "Florence", "lastName": "Bulago", "middleName": null, "email": "", "job": "Personal Secretary/ Com", "roomContact": "7164", "office": "Development Assisstance & Regional Cooperation"}, {"firstName": "Eunice", "lastName": "Asasira", "middleName": null, "email": "", "job": "Secretary/DARC", "roomContact": "7164", "office": "Development Assisstance & Regional Cooperation"}, {"firstName": "Andrew", "lastName": "Masaba", "middleName": null, "email": "", "job": "Economist", "roomContact": "7161", "office": "Development Assisstance & Regional Cooperation"}, {"firstName": "Doreen", "lastName": "Ankunda", "middleName": null, "email": "", "job": "Accts & Adim Assistant", "roomContact": "7337", "office": "Development Assisstance & Regional Cooperation"}, {"firstName": "Wiliam", "lastName": "Tukamuhwebwa", "middleName": null, "email": "", "job": "Economist", "roomContact": "7161", "office": "Development Assisstance & Regional Cooperation"}, {"firstName": "Denis", "lastName": "Muggagga", "middleName": null, "email": "", "job": "Economist", "roomContact": "7383", "office": "Development Assisstance & Regional Cooperation"}, {"firstName": "Molly", "lastName": "Opwonya", "middleName": "Apio", "email": "", "job": "Finance Officer/Legal", "roomContact": "7422", "office": "Development Assisstance & Regional Cooperation"}, {"firstName": "Joan", "lastName": "Kabakama", "middleName": null, "email": "", "job": "Economist", "roomContact": "7337", "office": "Development Assisstance & Regional Cooperation"}, {"firstName": "Lawrence", "lastName": "Kazibwe", "middleName": null, "email": "", "job": "Office Attendant", "roomContact": "7164", "office": "Development Assisstance & Regional Cooperation"}, {"firstName": "Anthony", "lastName": "Okello", "middleName": null, "email": "", "job": "Senior Economist", "roomContact": "7163", "office": "Development Assisstance & Regional Cooperation"}, {"firstName": "Emmanuel", "lastName": "Ogwang", "middleName": null, "email": "", "job": "Economist", "roomContact": "7163", "office": "Development Assisstance & Regional Cooperation"}, {"firstName": "Samuel", "lastName": "Opio", "middleName": null, "email": "", "job": "Economist", "roomContact": "7163", "office": "Development Assisstance & Regional Cooperation"}, {"firstName": "Tom", "lastName": "Kajungu", "middleName": null, "email": "", "job": "IT. App.Support Officer", "roomContact": "7163", "office": "Development Assisstance & Regional Cooperation"}, {"firstName": "Asuman", "lastName": "Baguma", "middleName": null, "email": "", "job": "IT.App.Support Officer", "roomContact": "7163", "office": "Development Assisstance & Regional Cooperation"}, {"firstName": "Laras", "lastName": "Engen", "middleName": null, "email": "", "job": "Consultantant", "roomContact": "7163", "office": "Development Assisstance & Regional Cooperation"}, {"firstName": "Joseph", "lastName": "Enyimu", "middleName": null, "email": "", "job": "Ag.Comm/EDPR", "roomContact": "7227", "office": "Economic Development Policy & Research"}, {"firstName": "Godfrey", "lastName": "K", "middleName": "Byamukama", "email": "", "job": "Ag AC/EDPR", "roomContact": "7174", "office": "Economic Development Policy & Research"}, {"firstName": "Passy", "lastName": "Washeba", "middleName": null, "email": "", "job": "Principal Economist", "roomContact": "7452", "office": "Economic Development Policy & Research"}, {"firstName": "James", "lastName": "Kibahiganira", "middleName": null, "email": "", "job": "Senior Economist", "roomContact": "7219", "office": "Economic Development Policy & Research"}, {"firstName": "Gadson", "lastName": "Abemigisha", "middleName": null, "email": "", "job": "Senior Economist", "roomContact": "7172", "office": "Economic Development Policy & Research"}, {"firstName": "Sheila", "lastName": "Nuwamanya", "middleName": "Lwamafa", "email": "", "job": "Senior Economist", "roomContact": "7432", "office": "Economic Development Policy & Research"}, {"firstName": "Rose", "lastName": "Kansiime", "middleName": null, "email": "", "job": "Personal Secretary", "roomContact": "7127", "office": "Economic Development Policy & Research"}, {"firstName": "Aida", "lastName": "Korubaro", "middleName": null, "email": "", "job": "Office Attendant", "roomContact": "7127", "office": "Economic Development Policy & Research"}, {"firstName": "Assy", "lastName": "Nabankema", "middleName": null, "email": "", "job": "Office Attendant", "roomContact": "7127", "office": "Economic Development Policy & Research"}, {"firstName": "Calyst", "lastName": "Ndyomugabi", "middleName": null, "email": "", "job": "Senior Economist", "roomContact": "7232", "office": "Economic Development Policy & Research"}, {"firstName": "Martha", "lastName": "Musimenta", "middleName": "B.", "email": "", "job": "Economist", "roomContact": "7232", "office": "Economic Development Policy & Research"}, {"firstName": "Mukisa", "lastName": "Muhammad", "middleName": null, "email": "", "job": "Economist", "roomContact": "7432", "office": "Economic Development Policy & Research"}, {"firstName": "Bridget", "lastName": "Nimungu", "middleName": null, "email": "", "job": "Economist", "roomContact": "7429", "office": "Economic Development Policy & Research"}, {"firstName": "Donald", "lastName": "Mbuga", "middleName": null, "email": "", "job": "Economist", "roomContact": "7429", "office": "Economic Development Policy & Research"}, {"firstName": "David", "lastName": "Bossa", "middleName": null, "email": "", "job": "Graduate Economist", "roomContact": "7432", "office": "Economic Development Policy & Research"}, {"firstName": "Marion", "lastName": "Mbabazi", "middleName": null, "email": "", "job": "Techinical Officer", "roomContact": "7168", "office": "Economic Development Policy & Research"}, {"firstName": "Sandra", "lastName": "Nakabiri", "middleName": null, "email": "", "job": "Economist", "roomContact": "7170", "office": "Economic Development Policy & Research"}, {"firstName": "Sylvia", "lastName": "Mutamba", "middleName": "Richbell", "email": "", "job": "Economist", "roomContact": "7172", "office": "Economic Development Policy & Research"}, {"firstName": "Andrew", "lastName": "Asasiira", "middleName": "Grace", "email": "", "job": "Economist", "roomContact": "7170", "office": "Economic Development Policy & Research"}, {"firstName": "Kassim", "lastName": "Mulumba", "middleName": null, "email": "", "job": "Economist", "roomContact": "7432", "office": "Economic Development Policy & Research"}, {"firstName": "Moses", "lastName": "Ogwapus", "middleName": null, "email": "", "job": "Ag.Comm TPD", "roomContact": "7148", "office": "Tax Policy Department"}, {"firstName": "Sizeline", "lastName": "Atukunda", "middleName": null, "email": "", "job": "Secretary", "roomContact": "7375", "office": "Tax Policy Department"}, {"firstName": "Francis", "lastName": "Twinamasiko", "middleName": null, "email": "", "job": "Ag.AC/TPD", "roomContact": "7309", "office": "Tax Policy Department"}, {"firstName": "Harriet", "lastName": "Namarome", "middleName": null, "email": "", "job": "Secretary", "roomContact": "7155", "office": "Tax Policy Department"}, {"firstName": "Agnes", "lastName": "Namukasa", "middleName": null, "email": "", "job": "Office Attendant", "roomContact": "7155", "office": "Tax Policy Department"}, {"firstName": "Susan", "lastName": "Nakagoro", "middleName": null, "email": "", "job": "Principal Economist", "roomContact": "7277", "office": "Tax Policy Department"}, {"firstName": "Saul", "lastName": "Ongaria", "middleName": null, "email": "", "job": "Principal Economist", "roomContact": "7154", "office": "Tax Policy Department"}, {"firstName": "Samuel", "lastName": "Kiyingi", "middleName": null, "email": "", "job": "Senior Economist", "roomContact": "7154", "office": "Tax Policy Department"}, {"firstName": "Isaac", "lastName": "Arinaitwe", "middleName": null, "email": "", "job": "Senior Economist", "roomContact": "7153", "office": "Tax Policy Department"}, {"firstName": "Daniel", "lastName": "Mbabazize", "middleName": null, "email": "", "job": "FO/ Legal", "roomContact": "7152", "office": "Tax Policy Department"}, {"firstName": "Ronald", "lastName": "Jabo", "middleName": null, "email": "", "job": "Economist", "roomContact": "7420", "office": "Tax Policy Department"}, {"firstName": "Eric", "lastName": "Kakaire", "middleName": null, "email": "", "job": "Graduate Economist", "roomContact": "7420", "office": "Tax Policy Department"}, {"firstName": "Peter", "lastName": "Ogolo", "middleName": "Obol", "email": "", "job": "Economist", "roomContact": "7427", "office": "Tax Policy Department"}, {"firstName": "Vanessa", "lastName": "Ihunde", "middleName": null, "email": "", "job": "Economist", "roomContact": "7427", "office": "Tax Policy Department"}, {"firstName": "Stella", "lastName": "Nabakooza", "middleName": null, "email": "", "job": "Economist", "roomContact": "7427", "office": "Tax Policy Department"}, {"firstName": "Clare", "lastName": "Bashasha", "middleName": "Ninsiima", "email": "", "job": "Economist", "roomContact": "7446", "office": "Tax Policy Department"}, {"firstName": "Gerald", "lastName": "Namoma", "middleName": null, "email": "", "job": "Economist", "roomContact": "7426", "office": "Tax Policy Department"}, {"firstName": "Anthony", "lastName": "Maraka", "middleName": null, "email": "", "job": "Economist", "roomContact": "7426", "office": "Tax Policy Department"}, {"firstName": "Farida", "lastName": "Murungi", "middleName": "Bahemuka", "email": "", "job": "Finance Officer/ Legal", "roomContact": "7426", "office": "Tax Policy Department"}, {"firstName": "Sandra", "lastName": "Kabugarure", "middleName": null, "email": "", "job": "Graduate Economist", "roomContact": "7277", "office": "Tax Policy Department"}, {"firstName": "Godwin", "lastName": "Kakama", "middleName": null, "email": "", "job": "Comm. BPED", "roomContact": "7120", "office": "Budget Policy And Evaluation"}, {"firstName": "John", "lastName": "Muheirwoha", "middleName": null, "email": "", "job": "Ag. AC/BPED", "roomContact": "7289", "office": "Budget Policy And Evaluation"}, {"firstName": "Christine", "lastName": "Kanyesige", "middleName": null, "email": "", "job": "Personal Secretary/CBPED", "roomContact": "7176", "office": "Budget Policy And Evaluation"}, {"firstName": "Awekonimungu", "lastName": "Lilian", "middleName": null, "email": "", "job": "Office Attendant", "roomContact": "7176", "office": "Budget Policy And Evaluation"}, {"firstName": "Ceasar", "lastName": "Omara", "middleName": null, "email": "", "job": "Office Attendant", "roomContact": "7176", "office": "Budget Policy And Evaluation"}, {"firstName": "Robert", "lastName": "Ssekate", "middleName": null, "email": "", "job": "Principal Economist", "roomContact": "7421", "office": "Budget Policy And Evaluation"}, {"firstName": "Ambrose", "lastName": "Lotyanga", "middleName": null, "email": "", "job": "Principal Economist", "roomContact": "7421", "office": "Budget Policy And Evaluation"}, {"firstName": "Joseph", "lastName": "Majanga", "middleName": "Oloo", "email": "", "job": "Senior Economist", "roomContact": "7158", "office": "Budget Policy And Evaluation"}, {"firstName": "Sam", "lastName": "Omaido", "middleName": null, "email": "", "job": "Senior Economist", "roomContact": "7370", "office": "Budget Policy And Evaluation"}, {"firstName": "Charles", "lastName": "Matovu", "middleName": null, "email": "", "job": "Economist", "roomContact": "7441", "office": "Budget Policy And Evaluation"}, {"firstName": "Henry", "lastName": "Karoro", "middleName": null, "email": "", "job": "Senior Economist", "roomContact": "7151", "office": "Budget Policy And Evaluation"}, {"firstName": "Esther", "lastName": "Ayebare", "middleName": null, "email": "", "job": "Senior Economist", "roomContact": "7275", "office": "Budget Policy And Evaluation"}, {"firstName": "Beth", "lastName": "Ansiimire", "middleName": null, "email": "", "job": "Senior Economist", "roomContact": "7150", "office": "Budget Policy And Evaluation"}, {"firstName": "Ivan", "lastName": "Kasozi", "middleName": null, "email": "", "job": "Economist", "roomContact": "7150", "office": "Budget Policy And Evaluation"}, {"firstName": "Arnold", "lastName": "Bigabwa", "middleName": null, "email": "", "job": "Economist", "roomContact": "7150", "office": "Budget Policy And Evaluation"}, {"firstName": "Emmanuel", "lastName": "Ogwang", "middleName": null, "email": "", "job": "Economist", "roomContact": "7150", "office": "Budget Policy And Evaluation"}, {"firstName": "Collin", "lastName": "Tumwiine", "middleName": null, "email": "", "job": "Graduate Economist", "roomContact": "7150", "office": "Budget Policy And Evaluation"}, {"firstName": "Phiona", "lastName": "Natamba", "middleName": null, "email": "", "job": "Graduate Economist", "roomContact": "7150", "office": "Budget Policy And Evaluation"}, {"firstName": "Carol", "lastName": "C.A.Abigaba", "middleName": null, "email": "", "job": "Database Programmer", "roomContact": "7151", "office": "Budget Policy And Evaluation"}, {"firstName": "Alinda", "lastName": "John", "middleName": null, "email": "", "job": "Economist", "roomContact": "7151", "office": "Budget Policy And Evaluation"}, {"firstName": "Lydia", "lastName": "Kobusinge", "middleName": null, "email": "", "job": "Economist", "roomContact": "7151", "office": "Budget Policy And Evaluation"}, {"firstName": "Stuart", "lastName": "Katungi", "middleName": null, "email": "", "job": "Database Programmer", "roomContact": "7151", "office": "Budget Policy And Evaluation"}, {"firstName": "Doreen", "lastName": "Ekallam", "middleName": "Sakwa", "email": "", "job": "Database Programmer", "roomContact": "7151", "office": "Budget Policy And Evaluation"}, {"firstName": "Beatrice", "lastName": "Ssekabembe", "middleName": null, "email": "", "job": "Admnistration Officer", "roomContact": "7171", "office": "Budget Policy And Evaluation"}, {"firstName": "Racheal", "lastName": "Mutesi", "middleName": null, "email": "", "job": "Secretary/ BPD", "roomContact": "7171", "office": "Budget Policy And Evaluation"}, {"firstName": "Patrick", "lastName": "Ocailap", "middleName": null, "email": "", "job": "DST", "roomContact": "7105", "office": "6th Floor"}, {"firstName": "Immaculate", "lastName": "Apuki", "middleName": null, "email": "", "job": "Personal Secretary", "roomContact": "7137", "office": "6th Floor"}, {"firstName": "Zephar", "lastName": "Bogere", "middleName": null, "email": "", "job": "Office Attendant", "roomContact": "7137", "office": "6th Floor"}, {"firstName": "Moses", "lastName": "Kaggwa", "middleName": null, "email": "", "job": "Ag.Director Econ. Affairs", "roomContact": "7107", "office": "6th Floor"}, {"firstName": "Joyce", "lastName": "Mudondo", "middleName": null, "email": "", "job": "Secretary/DEA", "roomContact": "7139", "office": "6th Floor"}, {"firstName": "Gladys", "lastName": "Nambozo", "middleName": null, "email": "", "job": "Office Attendant", "roomContact": "7139", "office": "6th Floor"}, {"firstName": "Kenneth", "lastName": "Mugambe", "middleName": null, "email": "", "job": "Director Budget", "roomContact": "7106", "office": "6th Floor"}, {"firstName": "Charles", "lastName": "Byaruhanga", "middleName": null, "email": "", "job": "Advisor Budget", "roomContact": "7147", "office": "6th Floor"}, {"firstName": "Rosemary", "lastName": "Amoding", "middleName": null, "email": "", "job": "Sen Personal Secretary /DB", "roomContact": "7138", "office": "6th Floor"}, {"firstName": "Ruth", "lastName": "Nantaba", "middleName": null, "email": "", "job": "Office Attendant", "roomContact": "7138", "office": "6th Floor"}, {"firstName": "Monday", "lastName": "Sylvester", "middleName": "Brian", "email": "", "job": "Office Attendant", "roomContact": "7138", "office": "6th Floor"}, {"firstName": "Ismael", "lastName": "Magona", "middleName": null, "email": "", "job": "Com/PAD", "roomContact": "7144", "office": "Public Administration Department"}, {"firstName": "Zziwa", "lastName": "Moses", "middleName": null, "email": "", "job": "AC/PAD", "roomContact": "7142", "office": "Public Administration Department"}, {"firstName": "Annet", "lastName": "Mugasa", "middleName": null, "email": "", "job": "Personal Secretary", "roomContact": "7145", "office": "Public Administration Department"}, {"firstName": "Rashidah", "lastName": "Kiggundu", "middleName": "Nagawa", "email": "", "job": "Personal Secretary/CPAD", "roomContact": "7141", "office": "Public Administration Department"}, {"firstName": "Jane", "lastName": "Namayanja", "middleName": null, "email": "", "job": "Principal Economist", "roomContact": "7329", "office": "Public Administration Department"}, {"firstName": "Mohammed", "lastName": "Kabaale", "middleName": null, "email": "", "job": "Principal Economist", "roomContact": "7143", "office": "Public Administration Department"}, {"firstName": "Godwin", "lastName": "Nuwamanya", "middleName": null, "email": "", "job": "Economist", "roomContact": "7150", "office": "Public Administration Department"}, {"firstName": "Tito", "lastName": "Okello", "middleName": null, "email": "", "job": "Economist", "roomContact": "7160", "office": "Public Administration Department"}, {"firstName": "Nancy", "lastName": "Rukundo", "middleName": null, "email": "", "job": "Economist", "roomContact": "7146", "office": "Public Administration Department"}, {"firstName": "Segamwenge", "lastName": "S.Geofrey", "middleName": null, "email": "", "job": "Senior Economist", "roomContact": "7146", "office": "Public Administration Department"}, {"firstName": "Tereza", "lastName": "Namwach", "middleName": null, "email": "", "job": "Principal Economist", "roomContact": "7146", "office": "Public Administration Department"}, {"firstName": "Angella", "lastName": "Mutesi", "middleName": null, "email": "", "job": "Economist", "roomContact": "7474", "office": "Public Administration Department"}, {"firstName": "George", "lastName": "Magoola", "middleName": null, "email": "", "job": "Driver", "roomContact": "7122", "office": "Public Administration Department"}, {"firstName": "Lawrence", "lastName": "Kazibwe", "middleName": null, "email": "", "job": "Office Attendant", "roomContact": "7145", "office": "Public Administration Department"}, {"firstName": "Dennis", "lastName": "Girardot", "middleName": null, "email": "", "job": "FINMAP", "roomContact": "7951", "office": "Public Administration Department"}, {"firstName": "Hon.", "lastName": "Kasaija", "middleName": "Matia", "email": "", "job": "Minister /MFPED", "roomContact": "7501", "office": "7th Floor"}, {"firstName": "Lilian", "lastName": "Musoke", "middleName": null, "email": "", "job": "Secretary /MFPED", "roomContact": "7131", "office": "7th Floor"}, {"firstName": "Jessica", "lastName": "Katongole", "middleName": null, "email": "", "job": "Secretary/MFPED", "roomContact": "7439", "office": "7th Floor"}, {"firstName": "Samuel", "lastName": "Obityo", "middleName": null, "email": "", "job": "Office Attendant", "roomContact": "7131", "office": "7th Floor"}, {"firstName": "Geoffrey", "lastName": "Maruki", "middleName": null, "email": "", "job": "Office Attendant", "roomContact": "7131", "office": "7th Floor"}, {"firstName": "Hon.", "lastName": "Bahati", "middleName": "David", "email": "", "job": "Minister of State/Planning", "roomContact": "7101", "office": "7th Floor"}, {"firstName": "Florence", "lastName": "Tatamba", "middleName": "Joan", "email": "", "job": "Prin. Personal Secretary/PL", "roomContact": "7132", "office": "7th Floor"}, {"firstName": "Grace", "lastName": "Ayerango", "middleName": null, "email": "", "job": "Steno Secretary", "roomContact": "7307", "office": "7th Floor"}, {"firstName": "Martin", "lastName": "Mitchell", "middleName": "Mayanja", "email": "", "job": "Office Attendant (PL)", "roomContact": "7132", "office": "7th Floor"}, {"firstName": "Hon", "lastName": "Anite", "middleName": "Evelyn", "email": "", "job": "Minister of State(PR&INV)", "roomContact": "7102", "office": "7th Floor"}, {"firstName": "Monica", "lastName": "Kwikiriza", "middleName": null, "email": "", "job": "Secretary /(PR&INV)", "roomContact": "7133", "office": "7th Floor"}, {"firstName": "Rosemary", "lastName": "Ayamo", "middleName": null, "email": "", "job": "Office Attendant//PR&INV)", "roomContact": "7133", "office": "7th Floor"}, {"firstName": "Hebert", "lastName": "Aheebwa", "middleName": null, "email": "", "job": "Driver (PL)", "roomContact": "7133", "office": "7th Floor"}, {"firstName": "Hon.", "lastName": "Ajedra", "middleName": null, "email": "", "job": "Minister of State/GD", "roomContact": "7103", "office": "7th Floor"}, {"firstName": "Annet", "lastName": "Nabunya", "middleName": null, "email": "", "job": "Personal Secretary /GD", "roomContact": "7134", "office": "7th Floor"}, {"firstName": "Grace", "lastName": "Aneno", "middleName": null, "email": "", "job": "Office Attendant /GD", "roomContact": "7233", "office": "7th Floor"}, {"firstName": "Chistopher", "lastName": "Bithum", "middleName": null, "email": "", "job": "Office Attendant/GD", "roomContact": "7233", "office": "7th Floor"}, {"firstName": "Keith", "lastName": "Muhakanizi", "middleName": null, "email": "", "job": "PS/ST", "roomContact": "7104", "office": "7th Floor"}, {"firstName": "Sauda", "lastName": "Kisiki", "middleName": null, "email": "", "job": "Sen. Personal Secretary/PS", "roomContact": "7135", "office": "7th Floor"}, {"firstName": "Layton", "lastName": "Nanjobe", "middleName": null, "email": "", "job": "Sen. Personal Secretary/PS", "roomContact": "7135", "office": "7th Floor"}, {"firstName": "Tom", "lastName": "Kirya", "middleName": null, "email": "", "job": "Office Attendant/PS", "roomContact": "7135", "office": "7th Floor"}, {"firstName": "Justine", "lastName": "Sendi", "middleName": null, "email": "", "job": "Receptionist Floor 7", "roomContact": "7136", "office": "7th Floor"}, {"firstName": "DrAlbert", "lastName": "Musisi", "middleName": null, "email": "", "job": "Com/MEPD", "roomContact": "7217", "office": "Macro Economic Policy"}, {"firstName": "Moses", "lastName": "Kabanda", "middleName": null, "email": "", "job": "Principal Economist", "roomContact": "7228", "office": "Macro Economic Policy"}, {"firstName": "Moses", "lastName": "Bekabye", "middleName": null, "email": "", "job": "Techinal Advisor/Econ.Affairs", "roomContact": "7226", "office": "Macro Economic Policy"}, {"firstName": "Joel", "lastName": "Kantu", "middleName": "Muhinda", "email": "", "job": "SE/Macro Modelling", "roomContact": "7229", "office": "Macro Economic Modelling"}, {"firstName": "Justine", "lastName": "Ayebare", "middleName": null, "email": "", "job": "SE/Macro Modelling", "roomContact": "7221", "office": "Macro Economic Modelling"}, {"firstName": "Wilson", "lastName": "Asiimwe", "middleName": null, "email": "", "job": "Economist/MMP", "roomContact": "7404", "office": "Macro Economic Modelling"}, {"firstName": "Priscilla", "lastName": "Kisakye", "middleName": null, "email": "", "job": "Economist", "roomContact": "7221", "office": "Macro Economic Modelling"}, {"firstName": "Susan", "lastName": "Ayinyo", "middleName": null, "email": "", "job": "Economist", "roomContact": "7221", "office": "Macro Economic Modelling"}, {"firstName": "Racheal", "lastName": "Nuwamanya", "middleName": null, "email": "", "job": "Economist", "roomContact": "7221", "office": "Macro Economic Modelling"}, {"firstName": "Davis", "lastName": "Vuningoma", "middleName": null, "email": "", "job": "Econ/Macro Modelling", "roomContact": "7404", "office": "Macro Economic Modelling"}, {"firstName": "Mustapha", "lastName": "Achidri", "middleName": null, "email": "", "job": "Ag. AC", "roomContact": "7222", "office": "Economic Analysis Section"}, {"firstName": "Rosett", "lastName": "Nakavuma", "middleName": null, "email": "", "job": "Senior Economist", "roomContact": "7220", "office": "Economic Analysis Section"}, {"firstName": "Caroline", "lastName": "Namukwaya", "middleName": null, "email": "", "job": "Economist", "roomContact": "7220", "office": "Economic Analysis Section"}, {"firstName": "Clare", "lastName": "Nyakahuma", "middleName": null, "email": "", "job": "Economist", "roomContact": "7220", "office": "Economic Analysis Section"}, {"firstName": "Anne", "lastName": "Nanziri", "middleName": null, "email": "", "job": "Graduate Economist", "roomContact": "7220", "office": "Economic Analysis Section"}, {"firstName": "Oscar", "lastName": "Ayebazibwe", "middleName": null, "email": "", "job": "Senior Economist", "roomContact": "7230", "office": "Fiscal Management Section"}, {"firstName": "Elaine", "lastName": "Abomwesigwa", "middleName": null, "email": "", "job": "Senior Economist", "roomContact": "7399", "office": "Fiscal Management Section"}, {"firstName": "Francis", "lastName": "Ahimbisibwe", "middleName": null, "email": "", "job": "Economist", "roomContact": "7399", "office": "Fiscal Management Section"}, {"firstName": "Obadia", "lastName": "Turinawe", "middleName": null, "email": "", "job": "Economist", "roomContact": "7399", "office": "Fiscal Management Section"}, {"firstName": "Yasin", "lastName": "Mayanja", "middleName": "Sadiq", "email": "", "job": "Principal Economist", "roomContact": "7225", "office": "External Financial Analysis Section"}, {"firstName": "Esther", "lastName": "Aguti", "middleName": null, "email": "", "job": "Economist", "roomContact": "7225", "office": "External Financial Analysis Section"}, {"firstName": "Flavia", "lastName": "Nasobora", "middleName": null, "email": "", "job": "Senior Economist", "roomContact": "7225", "office": "External Financial Analysis Section"}, {"firstName": "Musiime", "lastName": "Atuha", "middleName": "Joanah", "email": "", "job": "Economist", "roomContact": "7225", "office": "External Financial Analysis Section"}, {"firstName": "Esther", "lastName": "Nabaweesi", "middleName": null, "email": "", "job": "Personal Secretary", "roomContact": "7218", "office": "Administrative Section"}, {"firstName": "Juliet", "lastName": "Namono", "middleName": null, "email": "", "job": "Stenographer Secretary", "roomContact": "7218", "office": "Administrative Section"}, {"firstName": "Santa", "lastName": "Akum", "middleName": null, "email": "", "job": "Office Attendant", "roomContact": "7218", "office": "Administrative Section"}, {"firstName": "Denis", "lastName": "Otigo", "middleName": null, "email": "", "job": "Office Attendant", "roomContact": "7218", "office": "Administrative Section"}]